GoldMineDetection/__init__.py
GoldMineDetection/currentModel.pt
GoldMineDetection/data.yaml
GoldMineDetection/main.py
GoldMineYolo-0.0.12.dist-info/LICENSE
GoldMineYolo-0.0.12.dist-info/METADATA
GoldMineYolo-0.0.12.dist-info/WHEEL
GoldMineYolo-0.0.12.dist-info/top_level.txt
GoldMineYolo-0.0.12.dist-info/RECORD
