Metadata-Version: 2.1
Name: GoldMineYolo
Version: 0.0.12
Summary: For detecting abandoned gold mines in Ghana
Home-page: https://github.com/KeelanBoyle/EnviromentalRobotic.git
Author: Keelan Boyle
Author-email: kboyle@wpi.edu
Classifier: Programming Language :: Python :: 3
Classifier: License :: OSI Approved :: MIT License
Classifier: Operating System :: OS Independent
Requires-Python: >=3.7
License-File: LICENSE
